odoo/addons/sale_coupon_order_suggestion/README.rst
odoo/addons/sale_coupon_order_suggestion/__init__.py
odoo/addons/sale_coupon_order_suggestion/__manifest__.py
odoo/addons/sale_coupon_order_suggestion/i18n/sale_coupon_order_suggestion.pot
odoo/addons/sale_coupon_order_suggestion/models/__init__.py
odoo/addons/sale_coupon_order_suggestion/models/sale_order.py
odoo/addons/sale_coupon_order_suggestion/readme/CONTRIBUTORS.rst
odoo/addons/sale_coupon_order_suggestion/readme/DESCRIPTION.rst
odoo/addons/sale_coupon_order_suggestion/readme/USAGE.rst
odoo/addons/sale_coupon_order_suggestion/static/description/icon.png
odoo/addons/sale_coupon_order_suggestion/static/description/index.html
odoo/addons/sale_coupon_order_suggestion/static/src/js/suggest_promotion_widget.js
odoo/addons/sale_coupon_order_suggestion/static/src/xml/suggest_promotion.xml
odoo/addons/sale_coupon_order_suggestion/templates/assets.xml
odoo/addons/sale_coupon_order_suggestion/views/sale_order_views.xml
odoo13_addon_sale_coupon_order_suggestion-13.0.1.0.1.dev3.dist-info/METADATA
odoo13_addon_sale_coupon_order_suggestion-13.0.1.0.1.dev3.dist-info/WHEEL
odoo13_addon_sale_coupon_order_suggestion-13.0.1.0.1.dev3.dist-info/top_level.txt
odoo13_addon_sale_coupon_order_suggestion-13.0.1.0.1.dev3.dist-info/RECORD
